{"paragraphs":[{"title":"equip.cnsmr_afr_cmnt_base","text":"%jdbc(hive)\nSELECT DATE(updt_ts) as day, count(*) as recordscount FROM equip.cnsmr_afr_cmnt_base\ngroup by DATE(updt_ts) order by day desc limit 1;\n\n\n","user":"x135756","dateUpdated":"2020-06-30T05:40:41-0600","config":{"colWidth":11,"enabled":true,"results":{"0":{"graph":{"mode":"table","height":84,"optionOpen":false}}},"editorSetting":{"editOnDblClick":false,"language":"sql"},"editorMode":"ace/mode/sql","editorHide":true,"title":true},"settings":{"params":{},"forms":{}},"results":{"code":"SUCCESS","msg":[{"type":"TABLE","data":"day\trecordscount\n2020-06-29\t5231\n"}]},"apps":[],"jobName":"paragraph_1562061074887_1429954847","id":"20190702-035114_1031779129","dateCreated":"2019-07-02T03:51:14-0600","dateStarted":"2020-06-30T05:43:56-0600","dateFinished":"2020-06-30T05:44:21-0600","status":"FINISHED","progressUpdateIntervalMs":500,"focus":true,"$$hashKey":"object:30"},{"title":"equip.cnsmr_afr_base","text":"%jdbc(hive)\nSELECT DATE(updt_ts) as day, count(*) as recordscount FROM equip.cnsmr_afr_base\ngroup by DATE(updt_ts) order by day desc limit 1;","user":"x135756","dateUpdated":"2020-06-30T05:40:41-0600","config":{"colWidth":11,"enabled":true,"results":{"0":{"graph":{"mode":"table","height":84,"optionOpen":false}}},"editorSetting":{"editOnDblClick":false,"language":"sql"},"editorMode":"ace/mode/sql","editorHide":true,"title":true},"settings":{"params":{},"forms":{}},"results":{"code":"SUCCESS","msg":[{"type":"TABLE","data":"day\trecordscount\n2020-06-29\t5214\n"}]},"apps":[],"jobName":"paragraph_1562061212873_180506602","id":"20190702-035332_1821754695","dateCreated":"2019-07-02T03:53:32-0600","dateStarted":"2020-06-30T05:43:57-0600","dateFinished":"2020-06-30T05:44:05-0600","status":"FINISHED","progressUpdateIntervalMs":500,"$$hashKey":"object:31"},{"title":"equip.cnsmr_afr_trd_cncrn_base","text":"%jdbc(hive)\nSELECT DATE(updt_ts) as day, count(*) as recordscount FROM equip.cnsmr_afr_trd_cncrn_base\ngroup by DATE(updt_ts) order by day desc limit 1;","user":"x135756","dateUpdated":"2020-06-30T05:40:41-0600","config":{"colWidth":11,"enabled":true,"results":{"0":{"graph":{"mode":"table","height":84,"optionOpen":false}}},"editorSetting":{"editOnDblClick":false,"language":"sql"},"editorMode":"ace/mode/sql","editorHide":true,"title":true},"settings":{"params":{},"forms":{}},"results":{"code":"SUCCESS","msg":[{"type":"TABLE","data":"day\trecordscount\n2020-06-29\t5506\n"}]},"apps":[],"jobName":"paragraph_1562061315132_481485867","id":"20190702-035515_1146596894","dateCreated":"2019-07-02T03:55:15-0600","dateStarted":"2020-06-30T05:44:00-0600","dateFinished":"2020-06-30T05:44:07-0600","status":"FINISHED","progressUpdateIntervalMs":500,"$$hashKey":"object:32"},{"title":"equip.cnsmr_afr_vhcl_solr","text":"%jdbc(hive)\nSELECT DATE(updt_ts) as day, count(*) as recordscount FROM equip.cnsmr_afr_vhcl_solr\ngroup by DATE(updt_ts) order by day desc limit 1;","user":"x135756","dateUpdated":"2020-06-30T05:40:41-0600","config":{"colWidth":11,"enabled":true,"results":{"0":{"graph":{"mode":"table","height":84,"optionOpen":false}}},"editorSetting":{"editOnDblClick":false,"language":"sql"},"editorMode":"ace/mode/sql","editorHide":true,"title":true},"settings":{"params":{},"forms":{}},"results":{"code":"SUCCESS","msg":[{"type":"TABLE","data":"day\trecordscount\n2020-06-29\t16029\n"}]},"apps":[],"jobName":"paragraph_1562061317244_-763930999","id":"20190702-035517_959225587","dateCreated":"2019-07-02T03:55:17-0600","dateStarted":"2020-06-30T05:44:01-0600","dateFinished":"2020-06-30T05:44:14-0600","status":"FINISHED","progressUpdateIntervalMs":500,"$$hashKey":"object:33"},{"title":"equip.tchln_base","text":"%jdbc(hive)\nSELECT DATE(updt_ts) as day, count(*) as recordscount FROM equip.tchln_base\ngroup by DATE(updt_ts) order by day desc limit 1;","user":"x135756","dateUpdated":"2020-06-30T05:40:41-0600","config":{"colWidth":11,"enabled":true,"results":{"0":{"graph":{"mode":"table","height":84,"optionOpen":false}}},"editorSetting":{"editOnDblClick":false,"language":"sql"},"editorMode":"ace/mode/sql","editorHide":true,"title":true},"settings":{"params":{},"forms":{}},"results":{"code":"SUCCESS","msg":[{"type":"TABLE","data":"day\trecordscount\n2020-06-30\t597\n"}]},"apps":[],"jobName":"paragraph_1562061318404_550371244","id":"20190702-035518_1076908446","dateCreated":"2019-07-02T03:55:18-0600","dateStarted":"2020-06-30T05:44:05-0600","dateFinished":"2020-06-30T05:44:17-0600","status":"FINISHED","progressUpdateIntervalMs":500,"$$hashKey":"object:34"},{"title":"equip.tchln_cmnt_base","text":"%jdbc(hive)\nSELECT DATE(updt_ts) as day, count(*) as recordscount FROM equip.tchln_cmnt_base\ngroup by DATE(updt_ts) order by day desc limit 1;","user":"x135756","dateUpdated":"2020-06-30T05:40:41-0600","config":{"colWidth":11,"enabled":true,"results":{"0":{"graph":{"mode":"table","height":84,"optionOpen":false}}},"editorSetting":{"editOnDblClick":false,"language":"sql"},"editorMode":"ace/mode/sql","title":true,"editorHide":true},"settings":{"params":{},"forms":{}},"results":{"code":"SUCCESS","msg":[{"type":"TABLE","data":"day\trecordscount\n2020-06-30\t1187\n"}]},"apps":[],"jobName":"paragraph_1562061308811_-1529596634","id":"20190702-035508_424351090","dateCreated":"2019-07-02T03:55:08-0600","dateStarted":"2020-06-30T05:44:07-0600","dateFinished":"2020-06-30T05:44:20-0600","status":"FINISHED","progressUpdateIntervalMs":500,"$$hashKey":"object:35"},{"title":"equip.tchln_trd_base","text":"%jdbc(hive)\nSELECT DATE(updt_ts) as day, count(*) as recordscount FROM equip.tchln_trd_base\ngroup by DATE(updt_ts) order by day desc limit 1;","user":"x135756","dateUpdated":"2020-06-30T05:40:41-0600","config":{"colWidth":11,"enabled":true,"results":{"0":{"graph":{"mode":"table","height":84,"optionOpen":false}}},"editorSetting":{"editOnDblClick":false,"language":"sql"},"editorMode":"ace/mode/sql","editorHide":true,"title":true},"settings":{"params":{},"forms":{}},"results":{"code":"SUCCESS","msg":[{"type":"TABLE","data":"day\trecordscount\n2020-06-30\t597\n"}]},"apps":[],"jobName":"paragraph_1562061268699_1799438029","id":"20190702-035428_1509332858","dateCreated":"2019-07-02T03:54:28-0600","dateStarted":"2020-06-30T05:44:14-0600","dateFinished":"2020-06-30T05:44:23-0600","status":"FINISHED","progressUpdateIntervalMs":500,"$$hashKey":"object:36"},{"title":"equip.tchln_vhcl_solr","text":"%jdbc(hive)\nSELECT DATE(updt_ts) as day, count(*) as recordscount FROM equip.tchln_vhcl_solr\ngroup by DATE(updt_ts) order by day desc limit 1;","user":"x135756","dateUpdated":"2020-06-30T05:40:41-0600","config":{"colWidth":11,"enabled":true,"results":{"0":{"graph":{"mode":"table","height":84,"optionOpen":false}}},"editorSetting":{"editOnDblClick":false,"language":"sql"},"editorMode":"ace/mode/sql","title":true,"editorHide":true},"settings":{"params":{},"forms":{}},"results":{"code":"SUCCESS","msg":[{"type":"TABLE","data":"day\trecordscount\n2020-06-30\t501\n"}]},"apps":[],"jobName":"paragraph_1588679041632_-95304103","id":"20200505-054401_611310060","dateCreated":"2020-05-05T05:44:01-0600","dateStarted":"2020-06-30T05:44:17-0600","dateFinished":"2020-06-30T05:44:26-0600","status":"FINISHED","progressUpdateIntervalMs":500,"$$hashKey":"object:37"},{"title":"equip.inspct_base","text":"%jdbc(hive)\nSELECT DATE(updt_ts) as day, count(*) as recordscount FROM equip.inspct_base\ngroup by DATE(updt_ts) order by day desc limit 1;","user":"x135756","dateUpdated":"2020-06-30T05:40:41-0600","config":{"colWidth":11,"enabled":true,"results":{"0":{"graph":{"mode":"table","height":84,"optionOpen":false}}},"editorSetting":{"editOnDblClick":false,"language":"sql"},"editorMode":"ace/mode/sql","editorHide":true,"title":true},"settings":{"params":{},"forms":{}},"results":{"code":"SUCCESS","msg":[{"type":"TABLE","data":"day\trecordscount\n2020-06-30\t116596\n"}]},"apps":[],"jobName":"paragraph_1562061252851_882935500","id":"20190702-035412_1637965458","dateCreated":"2019-07-02T03:54:12-0600","dateStarted":"2020-06-30T05:44:20-0600","dateFinished":"2020-06-30T05:44:44-0600","status":"FINISHED","progressUpdateIntervalMs":500,"$$hashKey":"object:38"},{"title":"equip.inspct_vhcl_solr","text":"%jdbc(hive)\nSELECT DATE(updt_ts) as day, count(*) as recordscount FROM equip.inspct_vhcl_solr\ngroup by DATE(updt_ts) order by day desc limit 1;","user":"x135756","dateUpdated":"2020-06-30T05:40:41-0600","config":{"colWidth":11,"enabled":true,"results":{"0":{"graph":{"mode":"table","height":84,"optionOpen":false}}},"editorSetting":{"editOnDblClick":false,"language":"sql"},"editorMode":"ace/mode/sql","editorHide":true,"title":true},"settings":{"params":{},"forms":{}},"results":{"code":"SUCCESS","msg":[{"type":"TABLE","data":"day\trecordscount\n2020-06-30\t93929\n"}]},"apps":[],"jobName":"paragraph_1562061247704_142663292","id":"20190702-035407_1485310718","dateCreated":"2019-07-02T03:54:07-0600","dateStarted":"2020-06-30T05:44:21-0600","dateFinished":"2020-06-30T05:44:37-0600","status":"FINISHED","progressUpdateIntervalMs":500,"$$hashKey":"object:39"},{"user":"anonymous","dateUpdated":"2020-06-29T06:14:53-0600","config":{"colWidth":12,"enabled":true,"results":{},"editorSetting":{"editOnDblClick":false,"language":"scala"},"editorMode":"ace/mode/scala"},"settings":{"params":{},"forms":{}},"apps":[],"jobName":"paragraph_1579684193227_1211548000","id":"20200122-020953_2041327023","dateCreated":"2020-01-22T02:09:53-0700","status":"FINISHED","progressUpdateIntervalMs":500,"$$hashKey":"object:40"}],"name":"Techline, CA, Inspect","id":"2EF5NK4TS","angularObjects":{"2CHS8UYQQ:shared_process":[],"2CKX6DGQZ:shared_process":[],"2C8A4SZ9T_livy2:shared_process":[],"2CKX8WPU1:shared_process":[],"2C4U48MY3_spark2:shared_process":[],"2CK8A9MEG:anonymous:":[],"2CKAY1A8Y:shared_process":[],"2CKEKWY8Z:shared_process":[]},"config":{"isZeppelinNotebookCronEnable":true,"looknfeel":"default","personalizedMode":"false"},"info":{}}