{"paragraphs":[{"title":"equip.WRNTY_CVRG_CLAS_BASE","text":"%jdbc(hive)\nSELECT DATE(updt_ts) as day, count(*) as recordscount FROM equip.WRNTY_CVRG_CLAS_BASE \ngroup by DATE(updt_ts) order by day desc limit 1;","user":"x135756","dateUpdated":"2020-06-30T05:40:46-0600","config":{"colWidth":11,"enabled":true,"results":{"0":{"graph":{"mode":"table","height":88,"optionOpen":false}}},"editorSetting":{"editOnDblClick":false,"language":"sql"},"editorMode":"ace/mode/sql","title":true,"editorHide":true},"settings":{"params":{},"forms":{}},"results":{"code":"SUCCESS","msg":[{"type":"TABLE","data":"day\trecordscount\n2020-06-30\t65\n"}]},"apps":[],"jobName":"paragraph_1590697914768_1791731358","id":"20200528-143154_858533935","dateCreated":"2020-05-28T14:31:54-0600","dateStarted":"2020-06-30T05:44:22-0600","dateFinished":"2020-06-30T05:44:30-0600","status":"FINISHED","progressUpdateIntervalMs":500,"focus":true,"$$hashKey":"object:28"},{"title":"equip.ASGND_ENGNR_BASE","text":"%jdbc(hive)\nSELECT DATE(updt_ts) as day, count(*) as recordscount FROM equip.ASGND_ENGNR_BASE \ngroup by DATE(updt_ts) order by day desc limit 1;","user":"x135756","dateUpdated":"2020-06-30T05:40:46-0600","config":{"colWidth":11,"editorMode":"ace/mode/sql","results":{"0":{"graph":{"mode":"table","height":88,"optionOpen":false}}},"enabled":true,"editorSetting":{"language":"sql","editOnDblClick":false},"editorHide":true,"tableHide":false,"title":true},"settings":{"params":{},"forms":{}},"results":{"code":"SUCCESS","msg":[{"type":"TABLE","data":"day\trecordscount\n2020-06-29\t4750\n"}]},"apps":[],"jobName":"paragraph_1542368043382_517657860","id":"20181116-005800_1943241407","dateCreated":"2018-11-16T04:34:03-0700","dateStarted":"2020-06-30T05:44:23-0600","dateFinished":"2020-06-30T05:44:33-0600","status":"FINISHED","progressUpdateIntervalMs":500,"$$hashKey":"object:29"},{"title":"equip.DSTRBR_BASE","text":"%jdbc(hive)\nSELECT DATE(updt_ts) as day, count(*) as recordscount FROM equip.DSTRBR_BASE\ngroup by DATE(updt_ts) order by day desc limit 1;\n","user":"x135756","dateUpdated":"2020-06-30T05:40:46-0600","config":{"colWidth":11,"editorMode":"ace/mode/sql","results":{"0":{"graph":{"mode":"table","height":86,"optionOpen":true,"setting":{"multiBarChart":{"stacked":true}},"commonSetting":{},"keys":[],"groups":[],"values":[{"name":"numrecordsaffected","index":2,"aggr":"count"},{"name":"day","index":1,"aggr":"sum"}]},"helium":{}}},"enabled":true,"editorSetting":{"language":"sql","editOnDblClick":false},"editorHide":true,"tableHide":false,"title":true},"settings":{"params":{},"forms":{}},"results":{"code":"SUCCESS","msg":[{"type":"TABLE","data":"day\trecordscount\n2020-06-29\t568\n"}]},"apps":[],"jobName":"paragraph_1542368043383_517273111","id":"20181116-010124_690706602","dateCreated":"2018-11-16T04:34:03-0700","dateStarted":"2020-06-30T05:44:26-0600","dateFinished":"2020-06-30T05:44:36-0600","status":"FINISHED","progressUpdateIntervalMs":500,"$$hashKey":"object:30"},{"title":"equip.SVC_OPRTN_BASE","text":"%jdbc(hive)\nSELECT DATE(updt_ts) as day, count(*) as recordscount FROM equip.SVC_OPRTN_BASE\ngroup by DATE(updt_ts) order by day desc limit 1;","user":"x135756","dateUpdated":"2020-06-30T05:40:46-0600","config":{"colWidth":11,"editorMode":"ace/mode/sql","results":{"0":{"graph":{"mode":"table","height":88,"optionOpen":false}}},"enabled":true,"editorSetting":{"language":"sql","editOnDblClick":false},"editorHide":true,"lineNumbers":false,"title":true,"tableHide":false},"settings":{"params":{},"forms":{}},"results":{"code":"SUCCESS","msg":[{"type":"TABLE","data":"day\trecordscount\n2020-06-29\t138420\n"}]},"apps":[],"jobName":"paragraph_1542368043385_514964618","id":"20181116-010949_1671978148","dateCreated":"2018-11-16T04:34:03-0700","dateStarted":"2020-06-30T05:44:30-0600","dateFinished":"2020-06-30T05:45:02-0600","status":"FINISHED","progressUpdateIntervalMs":500,"$$hashKey":"object:31"},{"title":"equip.SVC_PRT_BASE","text":"%jdbc(hive)\nSELECT DATE(updt_ts) as day, count(*) as recordscount FROM equip.SVC_PRT_BASE\ngroup by DATE(updt_ts) order by day desc limit 1;","user":"x135756","dateUpdated":"2020-06-30T05:40:46-0600","config":{"colWidth":11,"enabled":true,"results":{"0":{"graph":{"mode":"table","height":88,"optionOpen":false}}},"editorSetting":{"language":"sql","editOnDblClick":false},"editorMode":"ace/mode/sql","editorHide":true,"tableHide":false,"title":true},"settings":{"params":{},"forms":{}},"results":{"code":"SUCCESS","msg":[{"type":"TABLE","data":"day\trecordscount\n2020-06-29\t158738\n"}]},"apps":[],"jobName":"paragraph_1542368835328_-973898134","id":"20181116-044715_701658012","dateCreated":"2018-11-16T04:47:15-0700","dateStarted":"2020-06-30T05:44:33-0600","dateFinished":"2020-06-30T05:45:00-0600","status":"FINISHED","progressUpdateIntervalMs":500,"$$hashKey":"object:32"},{"title":"equip.WRNTY_CMNT_BASE","text":"%jdbc(hive)\nSELECT DATE(updt_ts) as day, count(*) as recordscount FROM equip.WRNTY_CMNT_BASE\ngroup by DATE(updt_ts) order by day desc limit 1;","user":"x135756","dateUpdated":"2020-06-30T05:40:46-0600","config":{"colWidth":11,"enabled":true,"results":{"0":{"graph":{"mode":"table","height":88,"optionOpen":false}}},"editorSetting":{"language":"sql","editOnDblClick":false},"editorMode":"ace/mode/sql","editorHide":true,"tableHide":false,"title":true},"settings":{"params":{},"forms":{}},"results":{"code":"SUCCESS","msg":[{"type":"TABLE","data":"day\trecordscount\n2020-06-29\t219234\n"}]},"apps":[],"jobName":"paragraph_1542368837575_-162462704","id":"20181116-044717_111778475","dateCreated":"2018-11-16T04:47:17-0700","dateStarted":"2020-06-30T05:44:36-0600","dateFinished":"2020-06-30T05:45:02-0600","status":"FINISHED","progressUpdateIntervalMs":500,"$$hashKey":"object:33"},{"title":"equip.PNC_BASE","text":"%jdbc(hive)\nSELECT DATE(updt_ts) as day, count(*) as recordscount FROM equip.PNC_BASE\ngroup by DATE(updt_ts) order by day desc limit 1;\n","user":"x135756","dateUpdated":"2020-06-30T05:40:46-0600","config":{"colWidth":11,"enabled":true,"results":{"0":{"graph":{"mode":"table","height":92,"optionOpen":false}}},"editorSetting":{"language":"sql","editOnDblClick":false},"editorMode":"ace/mode/sql","editorHide":true,"tableHide":false,"title":true},"settings":{"params":{},"forms":{}},"results":{"code":"SUCCESS","msg":[{"type":"TABLE","data":"day\trecordscount\n2020-06-29\t20956\n"}]},"apps":[],"jobName":"paragraph_1542368838646_-995043999","id":"20181116-044718_1091030659","dateCreated":"2018-11-16T04:47:18-0700","dateStarted":"2020-06-30T05:44:36-0600","dateFinished":"2020-06-30T05:44:39-0600","status":"FINISHED","progressUpdateIntervalMs":500,"$$hashKey":"object:34"},{"title":"equip.PFP_BASE","text":"%jdbc(hive)\nSELECT DATE(updt_ts) as day, count(*) as recordscount FROM equip.PFP_BASE\ngroup by DATE(updt_ts) order by day desc limit 1;\n","user":"x135756","dateUpdated":"2020-06-30T05:40:46-0600","config":{"colWidth":11,"enabled":true,"results":{"0":{"graph":{"mode":"table","height":92,"optionOpen":false}}},"editorSetting":{"language":"sql","editOnDblClick":false},"editorMode":"ace/mode/sql","editorHide":true,"tableHide":false,"title":true},"settings":{"params":{},"forms":{}},"results":{"code":"SUCCESS","msg":[{"type":"TABLE","data":"day\trecordscount\n2020-06-29\t37965\n"}]},"apps":[],"jobName":"paragraph_1542368839230_-1515224512","id":"20181116-044719_260082250","dateCreated":"2018-11-16T04:47:19-0700","dateStarted":"2020-06-30T05:44:37-0600","dateFinished":"2020-06-30T05:44:42-0600","status":"FINISHED","progressUpdateIntervalMs":500,"$$hashKey":"object:35"},{"title":"equip.VHCL_SYMPTM_BASE","text":"%jdbc(hive)\nSELECT DATE(updt_ts) as day, count(*) as recordscount FROM equip.VHCL_SYMPTM_BASE\ngroup by DATE(updt_ts) order by day desc limit 1;\n","user":"x135756","dateUpdated":"2020-06-30T05:40:46-0600","config":{"colWidth":11,"enabled":true,"results":{"0":{"graph":{"mode":"table","height":92,"optionOpen":false}}},"editorSetting":{"language":"sql","editOnDblClick":false},"editorMode":"ace/mode/sql","editorHide":true,"tableHide":false,"title":true},"settings":{"params":{},"forms":{}},"results":{"code":"SUCCESS","msg":[{"type":"TABLE","data":"day\trecordscount\n2020-06-29\t1113\n"}]},"apps":[],"jobName":"paragraph_1542368925288_652205604","id":"20181116-044845_2088569099","dateCreated":"2018-11-16T04:48:45-0700","dateStarted":"2020-06-30T05:44:37-0600","dateFinished":"2020-06-30T05:44:44-0600","status":"FINISHED","progressUpdateIntervalMs":500,"$$hashKey":"object:36"},{"title":"equip.VHCL_TRBL_BASE","text":"%jdbc(hive)\nSELECT DATE(updt_ts) as day, count(*) as recordscount FROM equip.VHCL_TRBL_BASE\ngroup by DATE(updt_ts) order by day desc limit 1;\n\n\n\n","user":"x135756","dateUpdated":"2020-06-30T05:40:46-0600","config":{"colWidth":11,"enabled":true,"results":{"0":{"graph":{"mode":"table","height":92,"optionOpen":false}}},"editorSetting":{"language":"sql","editOnDblClick":false},"editorMode":"ace/mode/sql","editorHide":true,"tableHide":false,"title":true},"settings":{"params":{},"forms":{}},"results":{"code":"SUCCESS","msg":[{"type":"TABLE","data":"day\trecordscount\n2020-06-29\t86\n"}]},"apps":[],"jobName":"paragraph_1542368926881_1713727820","id":"20181116-044846_22827491","dateCreated":"2018-11-16T04:48:46-0700","dateStarted":"2020-06-30T05:44:39-0600","dateFinished":"2020-06-30T05:44:47-0600","status":"FINISHED","progressUpdateIntervalMs":500,"$$hashKey":"object:37"},{"title":"equip.WRNTY_CLM_BASE","text":"%jdbc(hive)\nSELECT DATE(updt_ts) as day, count(*) as recordscount FROM equip.WRNTY_CLM_BASE\ngroup by DATE(updt_ts) order by day desc limit 1;","user":"x135756","dateUpdated":"2020-06-30T05:40:46-0600","config":{"colWidth":11,"enabled":true,"results":{"0":{"graph":{"mode":"table","height":84,"optionOpen":false}}},"editorSetting":{"language":"sql","editOnDblClick":false},"editorMode":"ace/mode/sql","editorHide":true,"tableHide":false,"title":true},"settings":{"params":{},"forms":{}},"results":{"code":"SUCCESS","msg":[{"type":"TABLE","data":"day\trecordscount\n2020-06-29\t127200\n"}]},"apps":[],"jobName":"paragraph_1542369211009_-1805956763","id":"20181116-045331_536536368","dateCreated":"2018-11-16T04:53:31-0700","dateStarted":"2020-06-30T05:44:42-0600","dateFinished":"2020-06-30T05:45:00-0600","status":"FINISHED","progressUpdateIntervalMs":500,"$$hashKey":"object:38"},{"title":"equip.WRNTY_BSNS_TYP_BASE","text":"%jdbc(hive)\nSELECT DATE(updt_ts) as day, count(*) as recordscount FROM equip.WRNTY_BSNS_TYP_BASE\ngroup by DATE(updt_ts) order by day desc limit 1;\n","user":"x135756","dateUpdated":"2020-06-30T05:40:46-0600","config":{"colWidth":11,"enabled":true,"results":{"0":{"graph":{"mode":"table","height":84,"optionOpen":false}}},"editorSetting":{"language":"sql","editOnDblClick":false},"editorMode":"ace/mode/sql","editorHide":true,"tableHide":false,"title":true},"settings":{"params":{},"forms":{}},"results":{"code":"SUCCESS","msg":[{"type":"TABLE","data":"day\trecordscount\n2020-06-29\t29\n"}]},"apps":[],"jobName":"paragraph_1542369210793_-1525859564","id":"20181116-045330_1062103036","dateCreated":"2018-11-16T04:53:30-0700","dateStarted":"2020-06-30T05:44:44-0600","dateFinished":"2020-06-30T05:44:46-0600","status":"FINISHED","progressUpdateIntervalMs":500,"$$hashKey":"object:39"},{"title":"equip.VNDR_BASE","text":"%jdbc(hive)\nSELECT DATE(updt_ts) as day, count(*) as recordscount FROM equip.VNDR_BASE\ngroup by DATE(updt_ts) order by day desc limit 1;\n\n\n\n","user":"x135756","dateUpdated":"2020-06-30T05:40:46-0600","config":{"colWidth":11,"enabled":true,"results":{"0":{"graph":{"mode":"table","height":84,"optionOpen":false}}},"editorSetting":{"language":"sql","editOnDblClick":false},"editorMode":"ace/mode/sql","editorHide":true,"tableHide":false,"title":true},"settings":{"params":{},"forms":{}},"results":{"code":"SUCCESS","msg":[{"type":"TABLE","data":"day\trecordscount\n2020-06-29\t27634\n"}]},"apps":[],"jobName":"paragraph_1542368930744_1579850527","id":"20181116-044850_998507464","dateCreated":"2018-11-16T04:48:50-0700","dateStarted":"2020-06-30T05:44:44-0600","dateFinished":"2020-06-30T05:44:49-0600","status":"FINISHED","progressUpdateIntervalMs":500,"$$hashKey":"object:40"},{"title":"equip.VHCL_ENGN_MDL_BASE","text":"%jdbc(hive)\nSELECT DATE(updt_ts) as day, count(*) as recordscount FROM equip.VHCL_ENGN_MDL_BASE\ngroup by DATE(updt_ts) order by day desc limit 1;","user":"x135756","dateUpdated":"2020-06-30T05:40:46-0600","config":{"colWidth":11,"enabled":true,"results":{"0":{"graph":{"mode":"table","height":84,"optionOpen":false}}},"editorSetting":{"language":"sql","editOnDblClick":false},"editorMode":"ace/mode/sql","editorHide":true,"tableHide":false,"title":true},"settings":{"params":{},"forms":{}},"results":{"code":"SUCCESS","msg":[{"type":"TABLE","data":"day\trecordscount\n2020-06-29\t65\n"}]},"apps":[],"jobName":"paragraph_1542368931257_1382474341","id":"20181116-044851_1448515252","dateCreated":"2018-11-16T04:48:51-0700","dateStarted":"2020-06-30T05:44:45-0600","dateFinished":"2020-06-30T05:44:49-0600","status":"FINISHED","progressUpdateIntervalMs":500,"$$hashKey":"object:41"},{"title":"equip.VHCL_ENGN_MDL_BASE","text":"%jdbc(hive)\nSELECT DATE(updt_ts) as day, count(*) as recordscount FROM equip.PRT_BASE\ngroup by DATE(updt_ts) order by day desc limit 1;\n","user":"x135756","dateUpdated":"2020-06-30T05:40:46-0600","config":{"colWidth":11,"enabled":true,"results":{"0":{"graph":{"mode":"table","height":84,"optionOpen":false}}},"editorSetting":{"language":"sql","editOnDblClick":false},"editorMode":"ace/mode/sql","editorHide":true,"tableHide":false,"title":true},"settings":{"params":{},"forms":{}},"results":{"code":"SUCCESS","msg":[{"type":"TABLE","data":"day\trecordscount\n2020-06-29\t1384512\n"}]},"apps":[],"jobName":"paragraph_1542369112009_-1529861939","id":"20181116-045152_146974235","dateCreated":"2018-11-16T04:51:52-0700","dateStarted":"2020-06-30T05:44:46-0600","dateFinished":"2020-06-30T05:44:53-0600","status":"FINISHED","progressUpdateIntervalMs":500,"$$hashKey":"object:42"},{"title":"equip.PRDCTN_MDL_SRS_BASE","text":"%jdbc(hive)\nSELECT DATE(updt_ts) as day, count(*) as recordscount FROM equip.PRDCTN_MDL_SRS_BASE\ngroup by DATE(updt_ts) order by day desc limit 1;\n","user":"x135756","dateUpdated":"2020-06-30T05:40:46-0600","config":{"colWidth":11,"enabled":true,"results":{"0":{"graph":{"mode":"table","height":84,"optionOpen":false}}},"editorSetting":{"language":"sql","editOnDblClick":false},"editorMode":"ace/mode/sql","editorHide":true,"tableHide":false,"title":true},"settings":{"params":{},"forms":{}},"results":{"code":"SUCCESS","msg":[{"type":"TABLE","data":"day\trecordscount\n2020-06-29\t219\n"}]},"apps":[],"jobName":"paragraph_1542369145645_-1218737996","id":"20181116-045225_1118679385","dateCreated":"2018-11-16T04:52:25-0700","dateStarted":"2020-06-30T05:44:47-0600","dateFinished":"2020-06-30T05:44:51-0600","status":"FINISHED","progressUpdateIntervalMs":500,"$$hashKey":"object:43"},{"title":"equip.OPRTN_LCTN_BASE","text":"%jdbc(hive)\nSELECT DATE(updt_ts) as day, count(*) as recordscount FROM equip.OPRTN_LCTN_BASE\ngroup by DATE(updt_ts) order by day desc limit 1;\n","user":"x135756","dateUpdated":"2020-06-30T05:40:46-0600","config":{"colWidth":11,"enabled":true,"results":{"0":{"graph":{"mode":"table","height":84,"optionOpen":false}}},"editorSetting":{"language":"sql","editOnDblClick":false},"editorMode":"ace/mode/sql","editorHide":true,"tableHide":false,"title":true},"settings":{"params":{},"forms":{}},"results":{"code":"SUCCESS","msg":[{"type":"TABLE","data":"day\trecordscount\n2020-06-29\t112\n"}]},"apps":[],"jobName":"paragraph_1542368043387_515734116","id":"20181116-033038_545956714","dateCreated":"2018-11-16T04:34:03-0700","dateStarted":"2020-06-30T05:44:49-0600","dateFinished":"2020-06-30T05:44:53-0600","status":"FINISHED","progressUpdateIntervalMs":500,"$$hashKey":"object:44"},{"title":"equip.MDPRT_ASGNMT_BASE","text":"%jdbc(hive)\nSELECT DATE(updt_ts) as day, count(*) as recordscount FROM equip.MDPRT_ASGNMT_BASE\ngroup by DATE(updt_ts) order by day desc limit 1;\n","user":"x135756","dateUpdated":"2020-06-30T05:40:46-0600","config":{"colWidth":11,"enabled":true,"results":{"0":{"graph":{"mode":"table","height":84,"optionOpen":false}}},"editorSetting":{"language":"sql","editOnDblClick":false},"editorMode":"ace/mode/sql","title":true,"editorHide":true},"settings":{"params":{},"forms":{}},"results":{"code":"SUCCESS","msg":[{"type":"TABLE","data":"day\trecordscount\n2020-06-29\t61998\n"}]},"apps":[],"jobName":"paragraph_1562060914573_-849326641","id":"20190702-034834_613230769","dateCreated":"2019-07-02T03:48:34-0600","dateStarted":"2020-06-30T05:44:49-0600","dateFinished":"2020-06-30T05:44:56-0600","status":"FINISHED","progressUpdateIntervalMs":500,"$$hashKey":"object:45"},{"title":"equip.LBR_OPRTN_BASE","text":"%jdbc(hive)\nSELECT DATE(updt_ts) as day, count(*) as recordscount FROM equip.LBR_OPRTN_BASE\ngroup by DATE(updt_ts) order by day desc limit 1;\n","user":"x135756","dateUpdated":"2020-06-30T05:40:46-0600","config":{"colWidth":11,"enabled":true,"results":{"0":{"graph":{"mode":"table","height":84,"optionOpen":false}}},"editorSetting":{"language":"sql","editOnDblClick":false},"editorMode":"ace/mode/sql","title":true,"editorHide":true},"settings":{"params":{},"forms":{}},"results":{"code":"SUCCESS","msg":[{"type":"TABLE","data":"day\trecordscount\n2020-06-29\t44573\n"}]},"apps":[],"jobName":"paragraph_1562060910470_1873941398","id":"20190702-034830_581004506","dateCreated":"2019-07-02T03:48:30-0600","dateStarted":"2020-06-30T05:44:51-0600","dateFinished":"2020-06-30T05:44:55-0600","status":"FINISHED","progressUpdateIntervalMs":500,"$$hashKey":"object:46"},{"title":"equip.GLBL_SPLR_BASE","text":"%jdbc(hive)\nSELECT DATE(updt_ts) as day, count(*) as recordscount FROM equip.GLBL_SPLR_BASE\ngroup by DATE(updt_ts) order by day desc limit 1;\n","user":"x135756","dateUpdated":"2020-06-30T05:40:46-0600","config":{"colWidth":11,"enabled":true,"results":{"0":{"graph":{"mode":"table","height":84,"optionOpen":false}}},"editorSetting":{"language":"sql","editOnDblClick":false},"editorMode":"ace/mode/sql","title":true,"editorHide":true},"settings":{"params":{},"forms":{}},"results":{"code":"SUCCESS","msg":[{"type":"TABLE","data":"day\trecordscount\n2020-06-29\t1365\n"}]},"apps":[],"jobName":"paragraph_1562060940605_390981219","id":"20190702-034900_199892189","dateCreated":"2019-07-02T03:49:00-0600","dateStarted":"2020-06-30T05:44:53-0600","dateFinished":"2020-06-30T05:44:57-0600","status":"FINISHED","progressUpdateIntervalMs":500,"$$hashKey":"object:47"},{"title":"equip.wrnty_clm_vhcl_solr","text":"%jdbc(hive)\r\nSELECT DATE(updt_ts) as day, count(*) as recordscount FROM equip.wrnty_clm_vhcl_solr\r\ngroup by DATE(updt_ts) order by day desc limit 1;\r\n\r\n","user":"x135756","dateUpdated":"2020-06-30T05:40:47-0600","config":{"colWidth":11,"enabled":true,"results":{"0":{"graph":{"mode":"table","height":84,"optionOpen":false}}},"editorSetting":{"language":"sql","editOnDblClick":false},"editorMode":"ace/mode/sql","title":true,"editorHide":true},"settings":{"params":{},"forms":{}},"results":{"code":"SUCCESS","msg":[{"type":"TABLE","data":"day\trecordscount\n2020-06-29\t28012660\n"}]},"apps":[],"jobName":"paragraph_1562061870338_802166114","id":"20190702-040430_594064077","dateCreated":"2019-07-02T04:04:30-0600","dateStarted":"2020-06-30T05:44:53-0600","dateFinished":"2020-06-30T05:45:25-0600","status":"FINISHED","progressUpdateIntervalMs":500,"$$hashKey":"object:48"},{"title":"equip.mileage","text":"%jdbc(hive)\nSELECT DATE(updt_ts) as day, count(*) as recordscount FROM equip.mileage\ngroup by DATE(updt_ts) order by day desc limit 1;","user":"x135756","dateUpdated":"2020-06-30T05:40:47-0600","config":{"colWidth":11,"enabled":true,"results":{"0":{"graph":{"mode":"table","height":84,"optionOpen":false}}},"editorSetting":{"language":"sql","editOnDblClick":false},"editorMode":"ace/mode/sql","editorHide":true,"tableHide":false,"title":true},"settings":{"params":{},"forms":{}},"results":{"code":"SUCCESS","msg":[{"type":"TABLE","data":"day\trecordscount\n2020-06-29\t130\n"}]},"apps":[],"jobName":"paragraph_1542369552556_2114359217","id":"20181116-045912_1727827827","dateCreated":"2018-11-16T04:59:12-0700","dateStarted":"2020-06-30T05:44:55-0600","dateFinished":"2020-06-30T05:44:59-0600","status":"FINISHED","progressUpdateIntervalMs":500,"$$hashKey":"object:49"},{"title":"equip.vhcl","text":"%jdbc(hive)\nSELECT DATE(ls_up_tm_stmp) as day, count(*) as recordscount FROM equip.vhcl\ngroup by DATE(ls_up_tm_stmp) order by day desc limit 1;","user":"x135756","dateUpdated":"2020-06-30T05:40:47-0600","config":{"colWidth":11,"enabled":true,"results":{"0":{"graph":{"mode":"table","height":84,"optionOpen":false}}},"editorSetting":{"language":"sql","editOnDblClick":false},"editorMode":"ace/mode/sql","title":true,"editorHide":true},"settings":{"params":{},"forms":{}},"results":{"code":"SUCCESS","msg":[{"type":"TABLE","data":"day\trecordscount\n2020-06-29\t415029\n"}]},"apps":[],"jobName":"paragraph_1561969970799_-1114586913","id":"20190701-023250_1227828260","dateCreated":"2019-07-01T02:32:50-0600","dateStarted":"2020-06-30T05:44:56-0600","dateFinished":"2020-06-30T05:45:31-0600","status":"FINISHED","progressUpdateIntervalMs":500,"$$hashKey":"object:50"},{"title":"equip.DLR_DM","text":"%jdbc(hive)\nSELECT DATE(ls_up_tm_stmp) as day, count(*) as recordscount FROM equip.DLR_DM\ngroup by DATE(ls_up_tm_stmp) order by day desc limit 1;","user":"x135756","dateUpdated":"2020-06-30T05:40:47-0600","config":{"colWidth":11,"enabled":true,"results":{"0":{"graph":{"mode":"table","height":84,"optionOpen":false}}},"editorSetting":{"language":"sql","editOnDblClick":false},"editorMode":"ace/mode/sql","title":true,"editorHide":true},"settings":{"params":{},"forms":{}},"results":{"code":"SUCCESS","msg":[{"type":"TABLE","data":"day\trecordscount\n2020-06-29\t17599\n"}]},"apps":[],"jobName":"paragraph_1548668311978_-2069708416","id":"20190128-023831_1703141525","dateCreated":"2019-01-28T02:38:31-0700","dateStarted":"2020-06-30T05:44:57-0600","dateFinished":"2020-06-30T05:45:10-0600","status":"FINISHED","progressUpdateIntervalMs":500,"$$hashKey":"object:51"},{"title":"equip.vhcl_solr","text":"%jdbc(hive)\nSELECT DATE(ls_up_tm_stmp) as day, count(*) as recordscount FROM equip.vhcl_solr\ngroup by DATE(ls_up_tm_stmp) order by day desc limit 1;","user":"x135756","dateUpdated":"2020-06-30T05:40:47-0600","config":{"colWidth":11,"enabled":true,"results":{"0":{"graph":{"mode":"table","height":84,"optionOpen":false}}},"editorSetting":{"language":"sql","editOnDblClick":false},"editorMode":"ace/mode/sql","title":true,"editorHide":true},"settings":{"params":{},"forms":{}},"results":{"code":"SUCCESS","msg":[{"type":"TABLE","data":"day\trecordscount\n2020-06-29\t396815\n"}]},"apps":[],"jobName":"paragraph_1562060488586_-1801188318","id":"20190702-034128_1267239342","dateCreated":"2019-07-02T03:41:28-0600","dateStarted":"2020-06-30T05:44:59-0600","dateFinished":"2020-06-30T05:45:07-0600","status":"FINISHED","progressUpdateIntervalMs":500,"$$hashKey":"object:52"},{"user":"anonymous","dateUpdated":"2020-06-29T06:14:58-0600","config":{"colWidth":12,"enabled":true,"results":{},"editorSetting":{"language":"sql","editOnDblClick":false},"editorMode":"ace/mode/sql","editorHide":true},"settings":{"params":{},"forms":{}},"apps":[],"jobName":"paragraph_1562060520504_-1481416010","id":"20190702-034200_1355575226","dateCreated":"2019-07-02T03:42:00-0600","status":"FINISHED","progressUpdateIntervalMs":500,"$$hashKey":"object:53"}],"name":"Warranty and Vehicle","id":"2DV7XNXMK","angularObjects":{"2CHS8UYQQ:shared_process":[],"2CKX6DGQZ:shared_process":[],"2C8A4SZ9T_livy2:shared_process":[],"2CK8A9MEG:anonymous:":[],"2CKX8WPU1:shared_process":[],"2C4U48MY3_spark2:shared_process":[],"2CKAY1A8Y:shared_process":[],"2CKEKWY8Z:shared_process":[]},"config":{"isZeppelinNotebookCronEnable":true,"looknfeel":"default","personalizedMode":"false"},"info":{}}